[{"Date": "2024-12-04", "Time": "00:56:57.146610047", "Latitude": 42.089654, "Longitude": -75.970346, "State": "LOCKED"}, {"Date": "2024-12-04", "Time": "00:56:24.834198847", "Latitude": 42.089654, "Longitude": -75.970346, "State": "LOCKED"}, {"Date": "2024-12-04", "Time": "00:55:52.529619832", "Latitude": 42.089654, "Longitude": -75.970346, "State": "LOCKED"}, {"Date": "2024-12-04", "Time": "00:55:20.880034594", "Latitude": 42.089654, "Longitude": -75.970346, "State": "LOCKED"}, {"Date": "2024-12-04", "Time": "00:54:49.542151421", "Latitude": 42.089654, "Longitude": -75.970346, "State": "LOCKED"}, {"Date": "2024-12-04", "Time": "00:54:17.504512321", "Latitude": 42.089654, "Longitude": -75.970346, "State": "LOCKED"}, {"Date": "2024-12-04", "Time": "00:53:45.227208651", "Latitude": 42.089654, "Longitude": -75.970346, "State": "LOCKED"}, {"Date": "2024-12-04", "Time": "00:53:13.521460533", "Latitude": 42.089654, "Longitude": -75.970346, "State": "LOCKED"}, {"Date": "2024-12-04", "Time": "00:52:41.834908810", "Latitude": 42.089654, "Longitude": -75.970346, "State": "LOCKED"}, {"Date": "2024-12-04", "Time": "00:52:10.021558668", "Latitude": 42.089654, "Longitude": -75.970346, "State": "LOCKED"}, {"Date": "2024-12-04", "Time": "00:51:38.329217787", "Latitude": 42.089654, "Longitude": -75.970346, "State": "LOCKED"}, {"Date": "2024-12-04", "Time": "00:51:06.326522854", "Latitude": 42.089654, "Longitude": -75.970346, "State": "LOCKED"}, {"Date": "2024-12-04", "Time": "00:50:34.464101236", "Latitude": 42.089654, "Longitude": -75.970346, "State": "LOCKED"}, {"Date": "2024-12-04", "Time": "00:50:03.079737629", "Latitude": 42.089654, "Longitude": -75.970346, "State": "LOCKED"}, {"Date": "2024-12-04", "Time": "00:49:31.157182474", "Latitude": 42.089654, "Longitude": -75.970346, "State": "LOCKED"}, {"Date": "2024-12-04", "Time": "00:48:58.887192824", "Latitude": 42.089654, "Longitude": -75.970346, "State": "LOCKED"}, {"Date": "2024-12-04", "Time": "00:48:35.810546813", "Latitude": 42.089654, "Longitude": -75.970346, "State": "LOCKED"}, {"Date": "2024-12-04", "Time": "00:47:55.033896388", "Latitude": 42.089654, "Longitude": -75.970346, "State": "LOCKED"}, {"Date": "2024-12-04", "Time": "00:47:23.582256505", "Latitude": 42.089654, "Longitude": -75.970346, "State": "LOCKED"}, {"Date": "2024-12-04", "Time": "00:46:51.722466432", "Latitude": 42.089654, "Longitude": -75.970346, "State": "LOCKED"}, {"Date": "2024-12-04", "Time": "00:46:19.531449397", "Latitude": 42.089654, "Longitude": -75.970346, "State": "LOCKED"}, {"Date": "2024-12-04", "Time": "00:45:56.606979195", "Latitude": 42.089654, "Longitude": -75.970346, "State": "LOCKED"}, {"Date": "2024-12-04", "Time": "00:45:15.592880784", "Latitude": 42.089654, "Longitude": -75.970346, "State": "LOCKED"}, {"Date": "2024-12-04", "Time": "00:44:43.656763922", "Latitude": 42.089654, "Longitude": -75.970346, "State": "LOCKED"}, {"Date": "2024-12-04", "Time": "00:44:21.282075768", "Latitude": 42.089654, "Longitude": -75.970346, "State": "LOCKED"}, {"Date": "2024-12-04", "Time": "00:43:49.812540949", "Latitude": 42.089654, "Longitude": -75.970346, "State": "LOCKED"}, {"Date": "2024-12-04", "Time": "00:43:09.242915596", "Latitude": 42.089654, "Longitude": -75.970346, "State": "LOCKED"}, {"Date": "2024-12-04", "Time": "00:42:37.645616832", "Latitude": 42.089654, "Longitude": -75.970346, "State": "LOCKED"}, {"Date": "2024-12-04", "Time": "00:41:27.681583035", "Latitude": 42.089654, "Longitude": -75.970346, "State": "LOCKED"}, {"Date": "2024-12-04", "Time": "00:40:37.539735466", "Latitude": 42.089654, "Longitude": -75.970346, "State": "LOCKED"}, {"Date": "2024-12-04", "Time": "00:28:11.039148952", "Latitude": 42.089654, "Longitude": -75.970346, "State": "LOCKED"}, {"Date": "2024-12-04", "Time": "00:27:21.691459443", "Latitude": 42.089654, "Longitude": -75.970346, "State": "LOCKED"}, {"Date": "2024-12-04", "Time": "00:27:15.149958508", "Latitude": 42.089654, "Longitude": -75.970346, "State": "LOCKED"}, {"Date": "2024-12-04", "Time": "00:12:13.190562425", "Latitude": 42.089654, "Longitude": -75.970346, "State": "LOCKED"}, {"Date": "2024-12-03", "Time": "23:58:14.789349204", "Latitude": 42.089654, "Longitude": -75.970346, "State": "LOCKED"}, {"Date": "2024-12-03", "Time": "23:56:28.990230883", "Latitude": 42.089654, "Longitude": -75.970346, "State": "LOCKED"}, {"Date": "2024-12-03", "Time": "23:55:17.650787771", "Latitude": 42.089654, "Longitude": -75.970346, "State": "LOCKED"}, {"Date": "2024-12-03", "Time": "23:54:55.997927348", "Latitude": 42.089654, "Longitude": -75.970346, "State": "LOCKED"}, {"Date": "2024-12-03", "Time": "23:54:34.583467712", "Latitude": 42.089654, "Longitude": -75.970346, "State": "LOCKED"}, {"Date": "2024-12-03", "Time": "23:54:22.611984707", "Latitude": 42.089654, "Longitude": -75.970346, "State": "LOCKED"}, {"Date": "2024-12-03", "Time": "23:54:00.255456466", "Latitude": 42.089654, "Longitude": -75.970346, "State": "LOCKED"}, {"Date": "2024-12-03", "Time": "23:53:38.947133400", "Latitude": 42.089654, "Longitude": -75.970346, "State": "LOCKED"}, {"Date": "2024-12-03", "Time": "23:53:06.856130988", "Latitude": 42.089654, "Longitude": -75.970346, "State": "LOCKED"}, {"Date": "2024-12-03", "Time": "23:52:45.385125666", "Latitude": 42.089654, "Longitude": -75.970346, "State": "LOCKED"}, {"Date": "2024-12-03", "Time": "23:52:23.488653851", "Latitude": 42.089654, "Longitude": -75.970346, "State": "LOCKED"}, {"Date": "2024-12-03", "Time": "23:52:02.014112709", "Latitude": 42.089654, "Longitude": -75.970346, "State": "LOCKED"}]